cript_graph/__init__.py
cript_graph/core.py
cript_graph-0.0.0.dist-info/LICENSE
cript_graph-0.0.0.dist-info/METADATA
cript_graph-0.0.0.dist-info/WHEEL
cript_graph-0.0.0.dist-info/top_level.txt
cript_graph-0.0.0.dist-info/RECORD
