Metadata-Version: 2.1
Name: cript-graph
Version: 0.0.0
Summary: Plugin for CRIPT Python SDK, convert CRIPT graphs to networkx graphs and dot graphs for vizualization.
Home-page: https://github.com/InnocentBug/cript_graph
Author: Ludwig Schneider
License: MIT
Platform: any
Classifier: Development Status :: 3 - Alpha
Classifier: Topic :: Scientific/Engineering
Classifier: Programming Language :: Python :: 3
Classifier: Programming Language :: Python :: 3 :: Only
Classifier: Programming Language :: Python :: 3.7
Requires-Python: >=3.7
License-File: LICENSE
Requires-Dist: networkx
